[
  {
    "type": "action",
    "named": true,
    "fields": {},
    "children": {
      "multiple": true,
      "required": true,
      "types": [
        {
          "type": "completed_date",
          "named": true
        },
        {
          "type": "context_list",
          "named": true
        },
        {
          "type": "description",
          "named": true
        },
        {
          "type": "do_date_or_time",
          "named": true
        },
        {
          "type": "name",
          "named": true
        },
        {
          "type": "priority",
          "named": true
        },
        {
          "type": "state",
          "named": true
        },
        {
          "type": "story",
          "named": true
        }
      ]
    }
  },
  {
    "type": "action_list",
    "named": true,
    "fields": {},
    "children": {
      "multiple": true,
      "required": false,
      "types": [
        {
          "type": "action",
          "named": true
        }
      ]
    }
  },
  {
    "type": "completed_date",
    "named": true,
    "fields": {},
    "children": {
      "multiple": false,
      "required": true,
      "types": [
        {
          "type": "date",
          "named": true
        }
      ]
    }
  },
  {
    "type": "context_list",
    "named": true,
    "fields": {},
    "children": {
      "multiple": true,
      "required": true,
      "types": [
        {
          "type": "middle_context",
          "named": true
        },
        {
          "type": "tail_context",
          "named": true
        }
      ]
    }
  },
  {
    "type": "date",
    "named": true,
    "fields": {},
    "children": {
      "multiple": true,
      "required": true,
      "types": [
        {
          "type": "day",
          "named": true
        },
        {
          "type": "month",
          "named": true
        },
        {
          "type": "time",
          "named": true
        },
        {
          "type": "year",
          "named": true
        }
      ]
    }
  },
  {
    "type": "day",
    "named": true,
    "fields": {}
  },
  {
    "type": "description",
    "named": true,
    "fields": {}
  },
  {
    "type": "do_date_or_time",
    "named": true,
    "fields": {},
    "children": {
      "multiple": false,
      "required": true,
      "types": [
        {
          "type": "date",
          "named": true
        },
        {
          "type": "time",
          "named": true
        }
      ]
    }
  },
  {
    "type": "duration",
    "named": true,
    "fields": {}
  },
  {
    "type": "hour",
    "named": true,
    "fields": {}
  },
  {
    "type": "in_progress",
    "named": true,
    "fields": {}
  },
  {
    "type": "middle_context",
    "named": true,
    "fields": {}
  },
  {
    "type": "minute",
    "named": true,
    "fields": {}
  },
  {
    "type": "month",
    "named": true,
    "fields": {}
  },
  {
    "type": "priority",
    "named": true,
    "fields": {}
  },
  {
    "type": "state",
    "named": true,
    "fields": {},
    "children": {
      "multiple": false,
      "required": true,
      "types": [
        {
          "type": "blocked",
          "named": true
        },
        {
          "type": "cancelled",
          "named": true
        },
        {
          "type": "completed",
          "named": true
        },
        {
          "type": "in_progress",
          "named": true
        },
        {
          "type": "not_started",
          "named": true
        }
      ]
    }
  },
  {
    "type": "story",
    "named": true,
    "fields": {}
  },
  {
    "type": "tail_context",
    "named": true,
    "fields": {}
  },
  {
    "type": "time",
    "named": true,
    "fields": {},
    "children": {
      "multiple": true,
      "required": true,
      "types": [
        {
          "type": "duration",
          "named": true
        },
        {
          "type": "hour",
          "named": true
        },
        {
          "type": "minute",
          "named": true
        }
      ]
    }
  },
  {
    "type": "!",
    "named": false
  },
  {
    "type": "$",
    "named": false
  },
  {
    "type": "%",
    "named": false
  },
  {
    "type": "(",
    "named": false
  },
  {
    "type": ")",
    "named": false
  },
  {
    "type": "*",
    "named": false
  },
  {
    "type": "+",
    "named": false
  },
  {
    "type": ",",
    "named": false
  },
  {
    "type": "-",
    "named": false
  },
  {
    "type": ":",
    "named": false
  },
  {
    "type": "@",
    "named": false
  },
  {
    "type": "AM",
    "named": false
  },
  {
    "type": "D",
    "named": false
  },
  {
    "type": "PM",
    "named": false
  },
  {
    "type": "T",
    "named": false
  },
  {
    "type": "am",
    "named": false
  },
  {
    "type": "blocked",
    "named": true
  },
  {
    "type": "cancelled",
    "named": true
  },
  {
    "type": "completed",
    "named": true
  },
  {
    "type": "name",
    "named": true
  },
  {
    "type": "not_started",
    "named": true
  },
  {
    "type": "pm",
    "named": false
  },
  {
    "type": "year",
    "named": true
  }
]