[
  {
    "type": "action_list",
    "named": true,
    "fields": {},
    "children": {
      "multiple": true,
      "required": false,
      "types": [
        {
          "type": "root_action",
          "named": true
        }
      ]
    }
  },
  {
    "type": "child_action",
    "named": true,
    "fields": {},
    "children": {
      "multiple": true,
      "required": true,
      "types": [
        {
          "type": "child_icon",
          "named": true
        },
        {
          "type": "core_action",
          "named": true
        }
      ]
    }
  },
  {
    "type": "child_action_list",
    "named": true,
    "fields": {},
    "children": {
      "multiple": true,
      "required": true,
      "types": [
        {
          "type": "child_action",
          "named": true
        }
      ]
    }
  },
  {
    "type": "completed_date",
    "named": true,
    "fields": {},
    "children": {
      "multiple": false,
      "required": true,
      "types": [
        {
          "type": "date",
          "named": true
        }
      ]
    }
  },
  {
    "type": "context_list",
    "named": true,
    "fields": {},
    "children": {
      "multiple": true,
      "required": true,
      "types": [
        {
          "type": "context_icon",
          "named": true
        },
        {
          "type": "middle_context",
          "named": true
        },
        {
          "type": "tail_context",
          "named": true
        }
      ]
    }
  },
  {
    "type": "core_action",
    "named": true,
    "fields": {},
    "children": {
      "multiple": true,
      "required": true,
      "types": [
        {
          "type": "completed_date",
          "named": true
        },
        {
          "type": "context_list",
          "named": true
        },
        {
          "type": "description",
          "named": true
        },
        {
          "type": "do_date_or_time",
          "named": true
        },
        {
          "type": "id",
          "named": true
        },
        {
          "type": "name",
          "named": true
        },
        {
          "type": "priority",
          "named": true
        },
        {
          "type": "state",
          "named": true
        },
        {
          "type": "story",
          "named": true
        }
      ]
    }
  },
  {
    "type": "date",
    "named": true,
    "fields": {},
    "children": {
      "multiple": true,
      "required": true,
      "types": [
        {
          "type": "day",
          "named": true
        },
        {
          "type": "month",
          "named": true
        },
        {
          "type": "time",
          "named": true
        },
        {
          "type": "year",
          "named": true
        }
      ]
    }
  },
  {
    "type": "day",
    "named": true,
    "fields": {}
  },
  {
    "type": "description",
    "named": true,
    "fields": {},
    "children": {
      "multiple": false,
      "required": true,
      "types": [
        {
          "type": "desc_icon",
          "named": true
        }
      ]
    }
  },
  {
    "type": "do_date_or_time",
    "named": true,
    "fields": {},
    "children": {
      "multiple": true,
      "required": true,
      "types": [
        {
          "type": "date",
          "named": true
        },
        {
          "type": "do_date_icon",
          "named": true
        },
        {
          "type": "time",
          "named": true
        }
      ]
    }
  },
  {
    "type": "duration",
    "named": true,
    "fields": {},
    "children": {
      "multiple": false,
      "required": true,
      "types": [
        {
          "type": "duration_designator",
          "named": true
        }
      ]
    }
  },
  {
    "type": "hour",
    "named": true,
    "fields": {}
  },
  {
    "type": "id",
    "named": true,
    "fields": {},
    "children": {
      "multiple": true,
      "required": true,
      "types": [
        {
          "type": "id_icon",
          "named": true
        },
        {
          "type": "uuid",
          "named": true
        }
      ]
    }
  },
  {
    "type": "in_progress",
    "named": true,
    "fields": {}
  },
  {
    "type": "middle_context",
    "named": true,
    "fields": {},
    "children": {
      "multiple": false,
      "required": true,
      "types": [
        {
          "type": "context_separator",
          "named": true
        }
      ]
    }
  },
  {
    "type": "minute",
    "named": true,
    "fields": {}
  },
  {
    "type": "month",
    "named": true,
    "fields": {}
  },
  {
    "type": "priority",
    "named": true,
    "fields": {},
    "children": {
      "multiple": true,
      "required": true,
      "types": [
        {
          "type": "priority_icon",
          "named": true
        },
        {
          "type": "priority_number",
          "named": true
        }
      ]
    }
  },
  {
    "type": "priority_number",
    "named": true,
    "fields": {}
  },
  {
    "type": "root_action",
    "named": true,
    "fields": {},
    "children": {
      "multiple": true,
      "required": true,
      "types": [
        {
          "type": "child_action_list",
          "named": true
        },
        {
          "type": "core_action",
          "named": true
        }
      ]
    }
  },
  {
    "type": "state",
    "named": true,
    "fields": {},
    "children": {
      "multiple": false,
      "required": true,
      "types": [
        {
          "type": "blocked",
          "named": true
        },
        {
          "type": "cancelled",
          "named": true
        },
        {
          "type": "completed",
          "named": true
        },
        {
          "type": "in_progress",
          "named": true
        },
        {
          "type": "not_started",
          "named": true
        }
      ]
    }
  },
  {
    "type": "story",
    "named": true,
    "fields": {},
    "children": {
      "multiple": false,
      "required": true,
      "types": [
        {
          "type": "story_icon",
          "named": true
        }
      ]
    }
  },
  {
    "type": "tail_context",
    "named": true,
    "fields": {}
  },
  {
    "type": "time",
    "named": true,
    "fields": {},
    "children": {
      "multiple": true,
      "required": true,
      "types": [
        {
          "type": "duration",
          "named": true
        },
        {
          "type": "hour",
          "named": true
        },
        {
          "type": "minute",
          "named": true
        },
        {
          "type": "time_designator",
          "named": true
        }
      ]
    }
  },
  {
    "type": "uuid",
    "named": true,
    "fields": {},
    "children": {
      "multiple": true,
      "required": true,
      "types": [
        {
          "type": "uuid_random",
          "named": true
        },
        {
          "type": "uuid_time_high",
          "named": true
        },
        {
          "type": "uuid_time_mid",
          "named": true
        },
        {
          "type": "uuid_variant_random",
          "named": true
        },
        {
          "type": "uuid_version_random",
          "named": true
        }
      ]
    }
  },
  {
    "type": "uuid_time_mid",
    "named": true,
    "fields": {}
  },
  {
    "type": "uuid_variant_random",
    "named": true,
    "fields": {}
  },
  {
    "type": "uuid_version_random",
    "named": true,
    "fields": {}
  },
  {
    "type": "%",
    "named": false
  },
  {
    "type": "(",
    "named": false
  },
  {
    "type": ")",
    "named": false
  },
  {
    "type": "-",
    "named": false
  },
  {
    "type": ":",
    "named": false
  },
  {
    "type": "AM",
    "named": false
  },
  {
    "type": "PM",
    "named": false
  },
  {
    "type": "am",
    "named": false
  },
  {
    "type": "blocked",
    "named": true
  },
  {
    "type": "cancelled",
    "named": true
  },
  {
    "type": "child_icon",
    "named": true
  },
  {
    "type": "completed",
    "named": true
  },
  {
    "type": "context_icon",
    "named": true
  },
  {
    "type": "context_separator",
    "named": true
  },
  {
    "type": "desc_icon",
    "named": true
  },
  {
    "type": "do_date_icon",
    "named": true
  },
  {
    "type": "duration_designator",
    "named": true
  },
  {
    "type": "id_icon",
    "named": true
  },
  {
    "type": "name",
    "named": true
  },
  {
    "type": "not_started",
    "named": true
  },
  {
    "type": "pm",
    "named": false
  },
  {
    "type": "priority_icon",
    "named": true
  },
  {
    "type": "story_icon",
    "named": true
  },
  {
    "type": "time_designator",
    "named": true
  },
  {
    "type": "uuid_random",
    "named": true
  },
  {
    "type": "uuid_time_high",
    "named": true
  },
  {
    "type": "year",
    "named": true
  }
]